odoo/addons/sale_layout_category_hide_detail/README.rst
odoo/addons/sale_layout_category_hide_detail/__init__.py
odoo/addons/sale_layout_category_hide_detail/__manifest__.py
odoo/addons/sale_layout_category_hide_detail/i18n/es.po
odoo/addons/sale_layout_category_hide_detail/i18n/sale_layout_category_hide_detail.pot
odoo/addons/sale_layout_category_hide_detail/models/__init__.py
odoo/addons/sale_layout_category_hide_detail/models/account_invoice.py
odoo/addons/sale_layout_category_hide_detail/models/res_config_settings.py
odoo/addons/sale_layout_category_hide_detail/models/sale_layout_category.py
odoo/addons/sale_layout_category_hide_detail/models/sale_order.py
odoo/addons/sale_layout_category_hide_detail/readme/CONFIGURE.rst
odoo/addons/sale_layout_category_hide_detail/readme/CONTRIBUTORS.rst
odoo/addons/sale_layout_category_hide_detail/readme/DESCRIPTION.rst
odoo/addons/sale_layout_category_hide_detail/readme/USAGE.rst
odoo/addons/sale_layout_category_hide_detail/static/description/icon.png
odoo/addons/sale_layout_category_hide_detail/static/description/index.html
odoo/addons/sale_layout_category_hide_detail/tests/__init__.py
odoo/addons/sale_layout_category_hide_detail/tests/test_sale_layout_category_hide_detail.py
odoo/addons/sale_layout_category_hide_detail/views/account_portal_templates.xml
odoo/addons/sale_layout_category_hide_detail/views/invoice_report_templates.xml
odoo/addons/sale_layout_category_hide_detail/views/sale_layout_category_view.xml
odoo/addons/sale_layout_category_hide_detail/views/sale_order_report_templates.xml
odoo/addons/sale_layout_category_hide_detail/views/sale_portal_templates.xml
odoo11_addon_sale_layout_category_hide_detail-11.0.1.0.0.99.dev5.dist-info/METADATA
odoo11_addon_sale_layout_category_hide_detail-11.0.1.0.0.99.dev5.dist-info/WHEEL
odoo11_addon_sale_layout_category_hide_detail-11.0.1.0.0.99.dev5.dist-info/top_level.txt
odoo11_addon_sale_layout_category_hide_detail-11.0.1.0.0.99.dev5.dist-info/RECORD
